jbzd_imgcat.py
jbzd_imgcat-0.0.2.dist-info/LICENSE.txt
jbzd_imgcat-0.0.2.dist-info/METADATA
jbzd_imgcat-0.0.2.dist-info/WHEEL
jbzd_imgcat-0.0.2.dist-info/entry_points.txt
jbzd_imgcat-0.0.2.dist-info/top_level.txt
jbzd_imgcat-0.0.2.dist-info/RECORD
