Metadata-Version: 2.1
Name: jbzd-imgcat
Version: 0.0.2
Summary: jbzd.com.pl imgcat
Home-page: https://github.com/leszekbulawa/jbzd_imgcat
Author: Leszek Buława
Author-email: leszekbu@gmail.com
License: UNKNOWN
Keywords: jbzd jbzd.pl jbzd.com.pl imgcat
Platform: UNKNOWN
Classifier: Development Status :: 3 - Alpha
Classifier: Programming Language :: Python :: 3
License-File: LICENSE.txt
Requires-Dist: requests
Requires-Dist: BeautifulSoup4
